aliyunsdkedas/__init__.py
aliyunsdkedas/endpoint.py
aliyunsdkedas/request/__init__.py
aliyunsdkedas/request/v20170801/AbortAndRollbackChangeOrderRequest.py
aliyunsdkedas/request/v20170801/AbortChangeOrderRequest.py
aliyunsdkedas/request/v20170801/AddLogPathRequest.py
aliyunsdkedas/request/v20170801/AuthorizeApplicationRequest.py
aliyunsdkedas/request/v20170801/AuthorizeResourceGroupRequest.py
aliyunsdkedas/request/v20170801/AuthorizeRoleRequest.py
aliyunsdkedas/request/v20170801/BindEcsSlbRequest.py
aliyunsdkedas/request/v20170801/BindK8sSlbRequest.py
aliyunsdkedas/request/v20170801/BindSlbRequest.py
aliyunsdkedas/request/v20170801/ChangeDeployGroupRequest.py
aliyunsdkedas/request/v20170801/ContinuePipelineRequest.py
aliyunsdkedas/request/v20170801/ConvertK8sResourceRequest.py
aliyunsdkedas/request/v20170801/CreateApplicationScalingRuleRequest.py
aliyunsdkedas/request/v20170801/CreateConfigTemplateRequest.py
aliyunsdkedas/request/v20170801/CreateIDCImportCommandRequest.py
aliyunsdkedas/request/v20170801/CreateK8sConfigMapRequest.py
aliyunsdkedas/request/v20170801/CreateK8sIngressRuleRequest.py
aliyunsdkedas/request/v20170801/CreateK8sSecretRequest.py
aliyunsdkedas/request/v20170801/CreateK8sServiceRequest.py
aliyunsdkedas/request/v20170801/DeleteApplicationRequest.py
aliyunsdkedas/request/v20170801/DeleteApplicationScalingRuleRequest.py
aliyunsdkedas/request/v20170801/DeleteClusterMemberRequest.py
aliyunsdkedas/request/v20170801/DeleteClusterRequest.py
aliyunsdkedas/request/v20170801/DeleteConfigTemplateRequest.py
aliyunsdkedas/request/v20170801/DeleteDeployGroupRequest.py
aliyunsdkedas/request/v20170801/DeleteEcuRequest.py
aliyunsdkedas/request/v20170801/DeleteK8sApplicationRequest.py
aliyunsdkedas/request/v20170801/DeleteK8sConfigMapRequest.py
aliyunsdkedas/request/v20170801/DeleteK8sIngressRuleRequest.py
aliyunsdkedas/request/v20170801/DeleteK8sSecretRequest.py
aliyunsdkedas/request/v20170801/DeleteK8sServiceRequest.py
aliyun_python_sdk_edas-3.26.9.dist-info/LICENSE
aliyun_python_sdk_edas-3.26.9.dist-info/METADATA
aliyun_python_sdk_edas-3.26.9.dist-info/WHEEL
aliyun_python_sdk_edas-3.26.9.dist-info/top_level.txt
aliyun_python_sdk_edas-3.26.9.dist-info/RECORD
